firstProject.py
setup.py
firstProject.egg-info/PKG-INFO
firstProject.egg-info/SOURCES.txt
firstProject.egg-info/dependency_links.txt
firstProject.egg-info/top_level.txt