Metadata-Version: 1.0
Name: firstProject
Version: 1.3.0
Summary: A simple printer of nested lists v1.3.0
Home-page: http://www.headfirstlabs.com
Author: wallace.wang
Author-email: wangwen5366@163.com
License: UNKNOWN
Platform: UNKNOWN
